pickleclass/__init__.py
pickleclass/core.py
pickleclass-0.1.0.dist-info/LICENSE
pickleclass-0.1.0.dist-info/METADATA
pickleclass-0.1.0.dist-info/WHEEL
pickleclass-0.1.0.dist-info/RECORD
