Metadata-Version: 2.3
Name: pickleclass
Version: 0.1.0
Summary: 
License: MIT
Author: Miles Copeland Luce
Requires-Python: >=3.13,<4.0
Classifier: License :: OSI Approved :: MIT License
Classifier: Programming Language :: Python :: 3
Classifier: Programming Language :: Python :: 3.13
Requires-Dist: loguru (>=0.7.3,<0.8.0)
